README.rst
setup.cfg
setup.py
packt_calc/__init__.py
packt_calc/calc.py
packt_calc/cli.py
packt_calc.egg-info/PKG-INFO
packt_calc.egg-info/SOURCES.txt
packt_calc.egg-info/dependency_links.txt
packt_calc.egg-info/entry_points.txt
packt_calc.egg-info/requires.txt
packt_calc.egg-info/top_level.txt
packt_calc.egg-info/zip-safe